babu/__init__.py
babu/_internal/__init__.py
babu/_internal/app.py
babu/_internal/db.py
babu/_internal/route_parser.py
babu/_internal/route_parser_test.py
babu/db.py
babu/publishers.py
babu/response.py
babu/routing.py
babu-0.1.0.dist-info/entry_points.txt
babu-0.1.0.dist-info/LICENSE
babu-0.1.0.dist-info/WHEEL
babu-0.1.0.dist-info/METADATA
babu-0.1.0.dist-info/RECORD
