Metadata-Version: 2.1
Name: babu
Version: 0.1.0
Summary: A static site generator for Python
License: MPL-2.0
Author: Leigh Brenecki
Author-email: leigh@brenecki.id.au
Requires-Python: >=3.8
Classifier: License :: OSI Approved
Classifier: Programming Language :: Python :: 3
Classifier: Programming Language :: Python :: 3.8
Requires-Dist: attrs (>=19.3.0,<20.0.0)
Requires-Dist: click (>=7.0,<8.0)
Requires-Dist: lark-parser (>=0.8.1,<0.9.0)
Requires-Dist: ruamel.yaml (>=0.16.7,<0.17.0)
Requires-Dist: sqlalchemy (>=1.3,<2.0)
